maelstrom/__init__.py
maelstrom/eddy.py
maelstrom/estimator.py
maelstrom/maelstrom.py
maelstrom/orbit.py
maelstrom/periodogram.py
maelstrom/synthetic.py
maelstrom/utils.py
maelstrom/version.py
maelstrom-0.2.dist-info/LICENSE
maelstrom-0.2.dist-info/METADATA
maelstrom-0.2.dist-info/WHEEL
maelstrom-0.2.dist-info/top_level.txt
maelstrom-0.2.dist-info/RECORD
