Metadata-Version: 2.1
Name: maelstrom
Version: 0.2
Summary: A package to model the orbits of pulsating stars in binaries
Home-page: https://github.com/danhey/maelstrom
License: MIT
Platform: UNKNOWN
Requires-Dist: theano (>=1.0.0)
Requires-Dist: numpy (>=1.13.0)
Requires-Dist: pymc3 (>=3.5)
Requires-Dist: matplotlib (>=1.5.3)
Requires-Dist: astropy (>=1.3)
Requires-Dist: exoplanet
Requires-Dist: tqdm
Requires-Dist: seaborn
